{
    "types": [
        {
            "id": 1,
            "Nome": "Cultural",
            "Descrição": "Visita a museus, monumentos históricos, sítios arqueológicos e eventos culturais."
        },
        {
            "id": 2,
            "Nome": "Aventura",
            "Descrição": "Atividades ao ar livre como montanhismo, rafting, trekking e desportos radicais."
        },
        {
            "id": 3,
            "Nome": "Gastronómico",
            "Descrição": "Experiências culinárias, visitas a vinícolas, mercados locais e restaurantes típicos."
        },
        {
            "id": 4,
            "Nome": "Histórico",
            "Descrição": "Visita a locais com relevância histórica, castelos, palácios e sítios antigos."
        },
        {
            "id": 5,
            "Nome": "Religioso",
            "Descrição": "Visita a locais sagrados, peregrinações e eventos religiosos."
        },
        {
            "id": 6,
            "Nome": "Balnear",
            "Descrição": "Férias em destinos costeiros, praias e atividades aquáticas."
        },
        {
            "id": 7,
            "Nome": "Rural",
            "Descrição": "Experiência em ambientes rurais, quintas, aldeias e contacto com a vida agrícola."
        },
        {
            "id": 8,
            "Nome": "Urbano",
            "Descrição": "Exploração de grandes cidades, vida noturna, shopping e arquitetura moderna."
        },
        {
            "id": 9,
            "Nome": "Luxo",
            "Descrição": "Experiências premium com acomodações de alto padrão e serviços exclusivos."
        },
        {
            "id": 10,
            "Nome": "Exótico",
            "Descrição": "Destinos únicos e diferentes, com culturas e paisagens exóticas."
        }
    ]
}